lhcbdiracx/core/__init__.py
lhcbdiracx/core/models.py
lhcbdiracx/core/properties.py
lhcbdiracx/core/py.typed
lhcbdiracx/core/config/__init__.py
lhcbdiracx/core/config/schema.py
lhcbdiracx_core-0.0.7.dist-info/METADATA
lhcbdiracx_core-0.0.7.dist-info/WHEEL
lhcbdiracx_core-0.0.7.dist-info/entry_points.txt
lhcbdiracx_core-0.0.7.dist-info/top_level.txt
lhcbdiracx_core-0.0.7.dist-info/RECORD
